odoo/addons/contract_membership_delegated_partner/README.rst
odoo/addons/contract_membership_delegated_partner/__init__.py
odoo/addons/contract_membership_delegated_partner/__manifest__.py
odoo/addons/contract_membership_delegated_partner/i18n/contract_membership_delegated_partner.pot
odoo/addons/contract_membership_delegated_partner/i18n/de.po
odoo/addons/contract_membership_delegated_partner/i18n/es.po
odoo/addons/contract_membership_delegated_partner/i18n/it.po
odoo/addons/contract_membership_delegated_partner/models/__init__.py
odoo/addons/contract_membership_delegated_partner/models/contract.py
odoo/addons/contract_membership_delegated_partner/readme/CONFIGURE.rst
odoo/addons/contract_membership_delegated_partner/readme/CONTRIBUTORS.rst
odoo/addons/contract_membership_delegated_partner/readme/DESCRIPTION.rst
odoo/addons/contract_membership_delegated_partner/readme/INSTALL.rst
odoo/addons/contract_membership_delegated_partner/readme/USAGE.rst
odoo/addons/contract_membership_delegated_partner/static/description/icon.png
odoo/addons/contract_membership_delegated_partner/static/description/index.html
odoo/addons/contract_membership_delegated_partner/tests/__init__.py
odoo/addons/contract_membership_delegated_partner/tests/test_delegated_partner_contract.py
odoo/addons/contract_membership_delegated_partner/views/contract.xml
odoo14_addon_contract_membership_delegated_partner-14.0.1.0.1.dev7.dist-info/METADATA
odoo14_addon_contract_membership_delegated_partner-14.0.1.0.1.dev7.dist-info/WHEEL
odoo14_addon_contract_membership_delegated_partner-14.0.1.0.1.dev7.dist-info/top_level.txt
odoo14_addon_contract_membership_delegated_partner-14.0.1.0.1.dev7.dist-info/RECORD
